pixabay_python/__init__.py
pixabay_python/download_utils.py
pixabay_python/pixabay_python_core.py
pixabay_python/pixabay_python_enums.py
pixabay_python-1.1.0.dist-info/LICENSE
pixabay_python-1.1.0.dist-info/METADATA
pixabay_python-1.1.0.dist-info/WHEEL
pixabay_python-1.1.0.dist-info/top_level.txt
pixabay_python-1.1.0.dist-info/RECORD
