Metadata-Version: 2.1
Name: pixabay-python
Version: 1.1.0
Summary: a Python library for interacting with Pixabay api
Author-email: Farzad Shayanfar <farzad.shayanfar@hotmail.com>
License: 
Project-URL: Homepage, https://github.com/farzadshayanfar/pixabay_python
Keywords: pixabay,image,video,free image,free video,free stock media
Requires-Python: >=3.10
License-File: LICENSE
Requires-Dist: requests (>=2.30.0)
